{"CyC2018/CS-Notes": 512, "iluwatar/java-design-patterns": 684, "MisterBooo/LeetCodeAnimation": 54, "doocs/advanced-java": 121, "spring-projects/spring-boot": 23300, "elastic/elasticsearch": 28293, "kdn251/interviews": 47, "macrozheng/mall": 406, "spring-projects/spring-framework": 21345, "google/guava": 3289, "TheAlgorithms/Java": 536, "kon9chunkit/GitHub-Chinese-Top-Charts": 197, "square/retrofit": 2523, "apache/dubbo": 4757, "PhilJay/MPAndroidChart": 4715, "airbnb/lottie-android": 1351, "bumptech/glide": 4029, "Blankj/AndroidUtilCode": 1348, "NationalSecurityAgency/ghidra": 2700, "zxing/zxing": 1118, "netty/netty": 5606, "skylot/jadx": 927, "crossoverJie/JCSprout": 89, "ityouknow/spring-boot-examples": 104, "JakeWharton/butterknife": 1166, "jeecgboot/jeecg-boot": 2649, "alibaba/druid": 3368, "alibaba/fastjson": 3144, "greenrobot/EventBus": 550, "xkcoding/spring-boot-demo": 137, "scwang90/SmartRefreshLayout": 1372, "dbeaver/dbeaver": 11501, "lenve/vhr": 227, "CymChad/BaseRecyclerViewAdapterHelper": 3262, "qiurunze123/miaosha": 65, "wuyouzhuguli/SpringAll": 36, "SeleniumHQ/selenium": 7656, "hollischuang/toBeTopJavaer": 90, "alibaba/easyexcel": 1904, "signalapp/Signal-Android": 9175, "seata/seata": 2315, "alibaba/canal": 3327, "dromara/hutool": 1458, "alibaba/spring-cloud-alibaba": 1553, "google/gson": 1425, "apache/kafka": 0, "halo-dev/halo": 955, "alibaba/nacos": 4876, "ReactiveX/RxAndroid": 341, "google/ExoPlayer": 8532, "square/picasso": 1542, "didi/DoraemonKit": 579, "DrKLO/Telegram": 0, "Baseflow/PhotoView": 650, "jenkinsci/jenkins": 0, "apache/skywalking": 3950, "alibaba/Sentinel": 1639, "bazelbuild/bazel": 9092, "apache/flink": 0, "CarGuo/GSYVideoPlayer": 3230, "facebook/fresco": 2203, "elunez/eladmin": 560, "linlinjava/litemall": 334, "mybatis/mybatis-3": 1112, "Tencent/tinker": 1471, "freeCodeCamp/freeCodeCamp": 15620, "facebook/react": 10855, "twbs/bootstrap": 20924, "trekhleb/javascript-algorithms": 246, "d3/d3": 2092, "facebook/create-react-app": 7297, "axios/axios": 3300, "vercel/next.js": 10939, "mui-org/material-ui": 14270, "FortAwesome/Font-Awesome": 17690, "awesome-selfhosted/awesome-selfhosted": 638, "yangshun/tech-interview-handbook": 40, "angular/angular.js": 9029, "webpack/webpack": 8632, "ryanmcdermott/clean-code-javascript": 113, "hakimel/reveal.js": 2035, "typicode/json-server": 967, "atom/atom": 16755, "expressjs/express": 3614, "adam-p/markdown-here": 582, "h5bp/html5-boilerplate": 1231, "gatsbyjs/gatsby": 13083, "lodash/lodash": 4023, "scutan90/DeepLearning-500-questions": 176, "leonardomso/33-js-concepts": 36, "NARKOZ/hacker-scripts": 68, "mermaid-js/mermaid": 1560, "iamkun/dayjs": 921, "algorithm-visualizer/algorithm-visualizer": 83, "chinese-poetry/chinese-poetry": 149, "GitSquared/edex-ui": 559, "hexojs/hexo": 3734, "sahat/hackathon-starter": 604, "koajs/koa": 850, "public-apis/public-apis": 332, "donnemartin/system-design-primer": 195, "jackfrued/Python-100-Days": 523, "vinta/awesome-python": 226, "ytdl-org/youtube-dl": 24377, "tensorflow/models": 6670, "nvbn/thefuck": 611, "django/django": 0, "pallets/flask": 2215, "keras-team/keras": 10890, "josephmisiti/awesome-machine-learning": 72, "ansible/ansible": 29823, "scikit-learn/scikit-learn": 8937, "521xueweihan/HelloGitHub": 1897, "home-assistant/core": 24302, "psf/requests": 3476, "soimort/you-get": 0, "scrapy/scrapy": 2530, "minimaxir/big-list-of-naughty-strings": 80, "apache/superset": 7410, "python/cpython": 0, "deepfakes/faceswap": 713, "3b1b/manim": 919, "tiangolo/fastapi": 2489, "fighting41love/funNLP": 42, "0voice/interview_internal_reference": 42, "isocpp/CppCoreGuidelines": 948, "apachecn/AiLearning": 101, "pandas-dev/pandas": 21582, "XX-net/XX-Net": 12892, "laravel/laravel": 0, "danielmiessler/SecLists": 167, "blueimp/jQuery-File-Upload": 3308, "fzaninotto/Faker": 570, "symfony/symfony": 16611, "composer/composer": 6792, "laravel/framework": 15455, "guzzle/guzzle": 1716, "DesignPatternsPHP/DesignPatternsPHP": 107, "Seldaek/monolog": 686, "bcit-ci/CodeIgniter": 3183}