{"CyC2018/CS-Notes": 431, "iluwatar/java-design-patterns": 461, "MisterBooo/LeetCodeAnimation": 42, "doocs/advanced-java": 119, "spring-projects/spring-boot": 22825, "elastic/elasticsearch": 25175, "kdn251/interviews": 18, "macrozheng/mall": 384, "spring-projects/spring-framework": 20249, "google/guava": 2647, "TheAlgorithms/Java": 463, "kon9chunkit/GitHub-Chinese-Top-Charts": 53, "square/retrofit": 2399, "apache/dubbo": 4369, "PhilJay/MPAndroidChart": 2829, "airbnb/lottie-android": 1304, "bumptech/glide": 3743, "Blankj/AndroidUtilCode": 1240, "NationalSecurityAgency/ghidra": 1697, "zxing/zxing": 1109, "netty/netty": 5158, "skylot/jadx": 746, "crossoverJie/JCSprout": 59, "ityouknow/spring-boot-examples": 97, "JakeWharton/butterknife": 1071, "jeecgboot/jeecg-boot": 2635, "alibaba/druid": 1302, "alibaba/fastjson": 1551, "greenrobot/EventBus": 447, "xkcoding/spring-boot-demo": 70, "scwang90/SmartRefreshLayout": 1162, "dbeaver/dbeaver": 10110, "lenve/vhr": 88, "CymChad/BaseRecyclerViewAdapterHelper": 2867, "qiurunze123/miaosha": 31, "wuyouzhuguli/SpringAll": 24, "SeleniumHQ/selenium": 7480, "hollischuang/toBeTopJavaer": 61, "alibaba/easyexcel": 1876, "signalapp/Signal-Android": 7809, "seata/seata": 1812, "alibaba/canal": 2647, "dromara/hutool": 1457, "alibaba/spring-cloud-alibaba": 1218, "google/gson": 935, "apache/kafka": 0, "halo-dev/halo": 887, "alibaba/nacos": 4501, "ReactiveX/RxAndroid": 340, "google/ExoPlayer": 8003, "square/picasso": 1348, "didi/DoraemonKit": 450, "DrKLO/Telegram": 0, "Baseflow/PhotoView": 475, "jenkinsci/jenkins": 0, "apache/skywalking": 3887, "alibaba/Sentinel": 1311, "bazelbuild/bazel": 6966, "apache/flink": 0, "CarGuo/GSYVideoPlayer": 3216, "facebook/fresco": 2048, "elunez/eladmin": 527, "linlinjava/litemall": 308, "mybatis/mybatis-3": 981, "Tencent/tinker": 1054, "freeCodeCamp/freeCodeCamp": 15533, "facebook/react": 10203, "twbs/bootstrap": 20606, "trekhleb/javascript-algorithms": 162, "d3/d3": 2089, "facebook/create-react-app": 6248, "axios/axios": 3113, "vercel/next.js": 9817, "mui-org/material-ui": 13572, "FortAwesome/Font-Awesome": 12054, "awesome-selfhosted/awesome-selfhosted": 543, "yangshun/tech-interview-handbook": 33, "angular/angular.js": 8639, "webpack/webpack": 8457, "ryanmcdermott/clean-code-javascript": 76, "hakimel/reveal.js": 1452, "typicode/json-server": 444, "atom/atom": 16018, "expressjs/express": 3499, "adam-p/markdown-here": 305, "h5bp/html5-boilerplate": 1220, "gatsbyjs/gatsby": 12901, "lodash/lodash": 3828, "scutan90/DeepLearning-500-questions": 80, "leonardomso/33-js-concepts": 32, "NARKOZ/hacker-scripts": 34, "mermaid-js/mermaid": 1076, "iamkun/dayjs": 633, "algorithm-visualizer/algorithm-visualizer": 65, "chinese-poetry/chinese-poetry": 79, "GitSquared/edex-ui": 553, "hexojs/hexo": 3657, "sahat/hackathon-starter": 583, "koajs/koa": 819, "public-apis/public-apis": 328, "donnemartin/system-design-primer": 59, "jackfrued/Python-100-Days": 88, "vinta/awesome-python": 218, "ytdl-org/youtube-dl": 20417, "tensorflow/models": 5560, "nvbn/thefuck": 429, "django/django": 0, "pallets/flask": 2192, "keras-team/keras": 10698, "josephmisiti/awesome-machine-learning": 72, "ansible/ansible": 28773, "scikit-learn/scikit-learn": 7237, "521xueweihan/HelloGitHub": 1884, "home-assistant/core": 23276, "psf/requests": 3270, "soimort/you-get": 0, "scrapy/scrapy": 2040, "minimaxir/big-list-of-naughty-strings": 29, "apache/superset": 6310, "python/cpython": 0, "deepfakes/faceswap": 700, "3b1b/manim": 606, "tiangolo/fastapi": 1683, "fighting41love/funNLP": 28, "0voice/interview_internal_reference": 18, "isocpp/CppCoreGuidelines": 764, "apachecn/AiLearning": 98, "pandas-dev/pandas": 18176, "XX-net/XX-Net": 5166, "laravel/laravel": 0, "danielmiessler/SecLists": 145, "blueimp/jQuery-File-Upload": 3259, "fzaninotto/Faker": 494, "symfony/symfony": 16086, "composer/composer": 6619, "laravel/framework": 15455, "guzzle/guzzle": 1697, "DesignPatternsPHP/DesignPatternsPHP": 105, "Seldaek/monolog": 667, "bcit-ci/CodeIgniter": 3124}